anymate/__init__.py
anymate/helpers.py
anymate/models.py
anymate-1.0.13.dist-info/METADATA
anymate-1.0.13.dist-info/WHEEL
anymate-1.0.13.dist-info/top_level.txt
anymate-1.0.13.dist-info/RECORD
