Metadata-Version: 2.1
Name: anymate
Version: 1.0.13
Summary: Anymate SDK
Home-page: https://github.com/anymate/AnymatePythonSDK
Author: Anymate ApS
Author-email: simon@anymate.io
Classifier: Programming Language :: Python :: 3
Classifier: License :: OSI Approved :: MIT License
Classifier: Operating System :: OS Independent
Requires-Python: >=3.6
Requires-Dist: datetime
Requires-Dist: requests
Requires-Dist: pydantic
Requires-Dist: pyjwt
